bin/__init__.py
bin/microannotate-generate.py
bin/microannotate-view.py
microannotate/__init__.py
microannotate/annotatehelper.py
microannotate/generator.py
microannotate/utils.py
microannotate/viewer.py
microannotate-0.0.24.data/scripts/microannotate-generate.py
microannotate-0.0.24.data/scripts/microannotate-view.py
microannotate-0.0.24.dist-info/LICENSE
microannotate-0.0.24.dist-info/METADATA
microannotate-0.0.24.dist-info/WHEEL
microannotate-0.0.24.dist-info/top_level.txt
microannotate-0.0.24.dist-info/RECORD
