Metadata-Version: 2.1
Name: microannotate
Version: 0.0.24
Summary: Generate and view word-level annotate data
Home-page: UNKNOWN
Author: Marco Castelluccio
Author-email: mcastelluccio@mozilla.com
License: MPL2
Platform: UNKNOWN
Classifier: Programming Language :: Python :: 3.7
Classifier: Programming Language :: Python :: 3 :: Only
Classifier: License :: OSI Approved :: Mozilla Public License 2.0 (MPL 2.0)
Requires-Dist: aiofiles (~=0.6)
Requires-Dist: aiohttp (~=3.7)
Requires-Dist: pygit2 (~=1.4)
Requires-Dist: python-hglib (~=2.6)
Requires-Dist: tqdm (~=4.56)
